asmysql/__init__.py
asmysql/v1/__init__.py
asmysql/v1/_asmysql.py
asmysql/v1/_cursor_client.py
asmysql/v1/_error.py
asmysql/v1/_result.py
asmysql/v2/__init__.py
asmysql/v2/_asmysql.py
asmysql/v2/_engine.py
asmysql/v2/_error.py
asmysql/v2/_result.py
asmysql/v3dev/__init__.py
asmysql/v3dev/_asmysql.py
asmysql/v3dev/_async_engine.py
asmysql/v3dev/_async_result.py
asmysql/v3dev/_error.py
asmysql/v3dev/_sync_engine.py
asmysql/v3dev/_sync_pool.py
asmysql/v3dev/_sync_result.py
asmysql/v3dev/_types.py
asmysql-2.0.0.dist-info/WHEEL
asmysql-2.0.0.dist-info/METADATA
asmysql-2.0.0.dist-info/RECORD
