Metadata-Version: 2.3
Name: asmysql
Version: 2.0.0
Summary: An Asynchronous MySQL Client Engine Using Aiomysql.
Keywords: async,asyncio,mysql,aiomysql
Author: vastxiao
Author-email: vastxiao <vastxiao@gmail.com>
License: MIT License
Classifier: Programming Language :: Python :: 3
Classifier: Programming Language :: Python :: 3.9
Classifier: Programming Language :: Python :: 3.10
Classifier: Programming Language :: Python :: 3.11
Classifier: Programming Language :: Python :: 3.12
Classifier: Programming Language :: Python :: 3.13
Classifier: Programming Language :: Python :: 3.14
Classifier: Topic :: Software Development :: Libraries :: Python Modules
Classifier: Operating System :: POSIX :: Linux
Requires-Dist: aiomysql[rsa]>=0.3.2
Maintainer: vastxiao
Maintainer-email: vastxiao <vastxiao@gmail.com>
Requires-Python: >=3.9
Project-URL: Documentation, https://vastxiao.github.io/asmysql/
Project-URL: Gitee Repo, https://gitee.com/vastxiao/asmysql
Project-URL: Home, https://pypi.org/project/asmysql/
Project-URL: Repository, https://github.com/Vastxiao/asmysql
Project-URL: Vastxiao Blog, https://vastxiao.github.io/
